django_idom/__init__.py
django_idom/apps.py
django_idom/components.py
django_idom/config.py
django_idom/decorators.py
django_idom/hooks.py
django_idom/models.py
django_idom/py.typed
django_idom/types.py
django_idom/utils.py
django_idom/http/__init__.py
django_idom/http/urls.py
django_idom/http/views.py
django_idom/migrations/0001_initial.py
django_idom/migrations/0002_rename_created_at_componentparams_last_accessed.py
django_idom/migrations/0003_componentsession_delete_componentparams.py
django_idom/migrations/__init__.py
django_idom/static/django_idom/client.js
django_idom/templates/idom/component.html
django_idom/templatetags/__init__.py
django_idom/templatetags/idom.py
django_idom/websocket/__init__.py
django_idom/websocket/consumer.py
django_idom/websocket/paths.py
django_idom-3.0.1.dist-info/LICENSE
django_idom-3.0.1.dist-info/METADATA
django_idom-3.0.1.dist-info/WHEEL
django_idom-3.0.1.dist-info/top_level.txt
django_idom-3.0.1.dist-info/RECORD
