Metadata-Version: 2.1
Name: django-idom
Version: 3.0.1
Summary: Control the web with Python
Home-page: https://github.com/idom-team/django-idom
Author: Ryan Morshead
Author-email: ryan.morshead@gmail.com
License: MIT
Keywords: interactive,widgets,DOM,React
Platform: Linux
Platform: Mac OS X
Platform: Windows
Classifier: Framework :: Django
Classifier: Framework :: Django :: 4.0
Classifier: Operating System :: OS Independent
Classifier: Intended Audience :: Developers
Classifier: Intended Audience :: Science/Research
Classifier: Topic :: Multimedia :: Graphics
Classifier: Programming Language :: Python :: 3.8
Classifier: Programming Language :: Python :: 3.9
Classifier: Programming Language :: Python :: 3.10
Classifier: Environment :: Web Environment
Requires-Python: >=3.8
License-File: LICENSE
Requires-Dist: channels (>=4.0.0)
Requires-Dist: idom (<1.1.0,>=1.0.0)
Requires-Dist: aiofile (>=3.0)
Requires-Dist: dill (>=0.3.5)
Requires-Dist: typing-extensions
